odoo/addons/beesdoo_website_posorder_amount/README.rst
odoo/addons/beesdoo_website_posorder_amount/__init__.py
odoo/addons/beesdoo_website_posorder_amount/__manifest__.py
odoo/addons/beesdoo_website_posorder_amount/controllers/__init__.py
odoo/addons/beesdoo_website_posorder_amount/controllers/main.py
odoo/addons/beesdoo_website_posorder_amount/i18n/beesdoo_website_posorder_amount.pot
odoo/addons/beesdoo_website_posorder_amount/readme/CONTRIBUTORS.rst
odoo/addons/beesdoo_website_posorder_amount/readme/DESCRIPTION.rst
odoo/addons/beesdoo_website_posorder_amount/static/description/index.html
odoo/addons/beesdoo_website_posorder_amount/templates/portal_posorder_amount.xml
odoo12_addon_beesdoo_website_posorder_amount-12.0.1.0.0.99.dev16.dist-info/METADATA
odoo12_addon_beesdoo_website_posorder_amount-12.0.1.0.0.99.dev16.dist-info/WHEEL
odoo12_addon_beesdoo_website_posorder_amount-12.0.1.0.0.99.dev16.dist-info/top_level.txt
odoo12_addon_beesdoo_website_posorder_amount-12.0.1.0.0.99.dev16.dist-info/RECORD
