Metadata-Version: 2.1
Name: odoo12-addon-beesdoo-website-posorder-amount
Version: 12.0.1.0.0.99.dev16
Summary: Show the total amount of pos order in the website portal.
Home-page: https://github.com/beescoop/Obeesdoo
Author: Coop IT Easy SCRLfs
License: AGPL-3
Platform: UNKNOWN
Classifier: Programming Language :: Python
Classifier: Framework :: Odoo
Classifier: Framework :: Odoo :: 12.0
Classifier: License :: OSI Approved :: GNU Affero General Public License v3
Requires-Python: >=3.5
Requires-Dist: odoo (<12.1dev,>=12.0a)
